sistema_bancario/__init__.py
sistema_bancario/p3_sistema_bancario_POO.py
pacote_sistema_bancario-0.0.2.dist-info/METADATA
pacote_sistema_bancario-0.0.2.dist-info/WHEEL
pacote_sistema_bancario-0.0.2.dist-info/top_level.txt
pacote_sistema_bancario-0.0.2.dist-info/RECORD
