Metadata-Version: 2.4
Name: pacote-sistema-bancario
Version: 0.0.2
Summary: Pacote de sistema bancário desenvolvido em Python com POO
Author-email: Miguel Ângelo <miguelangelodasilva86@gmail.com>
License: MIT
Requires-Python: >=3.7
